[
    {
        "image": "./img/assets/batman/1966_batman.jpg",
        "name": "1966"
    },
      {
        "image": "./img/assets/batman/funny_batman.png",
        "name": "funny"
    },
      {
        "image": "./img/assets/batman/lego_batman.png",
        "name": "lego"
    },
      {
        "image": "./img/assets/batman/surprised_batman.jpg",
        "name": "surprised"
    },
      {
        "image": "./img/assets/batman/trollface_batman.jpg",
        "name": "trollface"
    },
      {
        "image": "./img/assets/batman/vector_batman.png",
        "name": "vector"
    }
]